Metadata-Version: 1.0
Name: gorille
Version: 0.0.1
Summary: The cyber-detect gorille module for ploting a 3D graph
Home-page: http://cyber-detect.eu/fr-produits-services-cybersecurite.html
Author: Cyber-Detect
Author-email: team@cyber-detect.com
License: Proprietary
Platform: UNKNOWN
